nalibsAWS/__base.py
nalibsAWS/__init__.py
nalibsAWS/__version.py
nalibsAWS/aws_sm_func.py
nalibsAWS/common.py
nalibsAWS/tmpl.dotenv_config.j2
nalibsAWS/x0_cli_cicd.py
nalibs_aws-0.3.0.dist-info/LICENSE
nalibs_aws-0.3.0.dist-info/METADATA
nalibs_aws-0.3.0.dist-info/WHEEL
nalibs_aws-0.3.0.dist-info/entry_points.txt
nalibs_aws-0.3.0.dist-info/top_level.txt
nalibs_aws-0.3.0.dist-info/RECORD
